GameVisionTargetingModel/__init__.py
GameVisionTargetingModel/setup_package.py
GameVisionTargetingModel/models/__init__.py
GameVisionTargetingModel/models/classification/__init__.py
GameVisionTargetingModel/models/classification/map/__init__.py
GameVisionTargetingModel/models/classification/map/v1/__init__.py
GameVisionTargetingModel/models/classification/map/v1/layers.py
GameVisionTargetingModel/models/classification/map/v1/map_classifier_v1.py
GameVisionTargetingModel/models/classification/map/v1/setup/__init__.py
GameVisionTargetingModel/models/classification/map/v1/setup/setup_of_input_layer.py
GameVisionTargetingModel/models/classification/map/v1/setup/setup_of_middle_layer.py
GameVisionTargetingModel/models/classification/map/v1/setup/setup_of_output_layer.py
GameVisionTargetingModel/models/classification/map/v1/setup/setup_of_preprocessing.py
GameVisionTargetingModel/models/classification/map/v1/setup/middle_layer/__init__.py
GameVisionTargetingModel/models/classification/map/v1/setup/middle_layer/connector.py
GameVisionTargetingModel/models/classification/map/v1/setup/middle_layer/decision.py
GameVisionTargetingModel/models/classification/map/v1/setup/middle_layer/first.py
GameVisionTargetingModel/models/classification/map/v1/setup/middle_layer/second.py
GameVisionTargetingModel/models/classification/map/v1/setup/middle_layer/third.py
GameVisionTargetingModel/singletons/__init__.py
GameVisionTargetingModel/singletons/singletons.py
GameVisionTargetingModel/tests/__init__.py
GameVisionTargetingModel/tests/configuration_test.py
GameVisionTargetingModel/tests/map_classifier_test.py
GameVisionTargetingModel/tests/pytest_test.py
GameVisionTargetingModel/variables/__init__.py
GameVisionTargetingModel/variables/model_settings.py
GameVisionTargetingModel/variables/normalise_settings.py
GameVisionTargetingModel/variables/training_settings.py
game_vision_targeting_model-0.0.9.dist-info/METADATA
game_vision_targeting_model-0.0.9.dist-info/WHEEL
game_vision_targeting_model-0.0.9.dist-info/top_level.txt
game_vision_targeting_model-0.0.9.dist-info/RECORD
