Metadata-Version: 2.1
Name: game-vision-targeting-model
Version: 0.0.9
Summary: A small example package
Author-email: Kent vejrup Madsen <kent.vejrup.madsen@outlook.com>
License: Copyright 2023 Kent Vejrup Madsen
Project-URL: Changelog, https://github.com/KentVejrupMadsen/gv-targeting-model/blob/main/Changelog.md
Project-URL: Homepage, https://github.com/KentVejrupMadsen/gv-targeting-model
Project-URL: Issues, https://github.com/KentVejrupMadsen/gv-targeting-model/issues
Project-URL: License, https://github.com/KentVejrupMadsen/gv-targeting-model/blob/main/License.md
Project-URL: Requirements, https://raw.githubusercontent.com/KentVejrupMadsen/gv-targeting-model/main/requirements.txt
Keywords: game,vision,machine,learning
Classifier: Programming Language :: Python :: 3
Classifier: Development Status :: 2 - Pre-Alpha
Classifier: License :: OSI Approved :: MIT License
Requires-Python: >=3.7
Requires-Dist: wheel
Requires-Dist: keras
Requires-Dist: tensorflow
Requires-Dist: numpy
Provides-Extra: dev
Requires-Dist: pytest ; extra == 'dev'
Provides-Extra: notebook
Requires-Dist: jupyterlab ; extra == 'notebook'
